[
    {
        "Station": "Bella",
        "Facility": "E-DME",
        "Ident": "BEL",
        "Periodicity": 365,
        "TypeDME": "Fernau",
        "NoofTxDME": 2,
        "DMEFrequency": 114.65,
        "DMEProcedure": "LFV.FI.P.09-03C",
        "NationalRegulation": "BL 8-2",
        "InternationalStandard": "ICAO Annex 10 Vol 1",
        "Country": "Denmark"
    },
    {
        "Station": "Esbjerg",
        "Facility": "E-DME",
        "Ident": "ESE",
        "Periodicity": 365,
        "TypeDME": null,
        "NoofTxDME": 2,
        "DMEFrequency": 116.6,
        "DMEProcedure": "LFV.FI.P.09-03C",
        "NationalRegulation": "BL 8-2",
        "InternationalStandard": "ICAO Annex 10 Vol 1",
        "Country": "Denmark"
    },
    {
        "Station": "Lemme",
        "Facility": "E-DME",
        "Ident": "LME",
        "Periodicity": 365,
        "TypeDME": "Fernau",
        "NoofTxDME": 2,
        "DMEFrequency": 115.35,
        "DMEProcedure": "LFV.FI.P.09-03C",
        "NationalRegulation": "BL 8-2",
        "InternationalStandard": "ICAO Annex 10 Vol 1",
        "Country": "Denmark"
    },
    {
        "Station": "Ramme",
        "Facility": "E-DME",
        "Ident": "RAM",
        "Periodicity": 365,
        "TypeDME": null,
        "NoofTxDME": 2,
        "DMEFrequency": 111.85,
        "DMEProcedure": "LFV.FI.P.09-03C",
        "NationalRegulation": "BL 8-2",
        "InternationalStandard": "ICAO Annex 10 Vol 1",
        "Country": "Denmark"
    },
    {
        "Station": "Vamme ",
        "Facility": "E-DME",
        "Ident": "VAM",
        "Periodicity": 365,
        "TypeDME": "Fernau",
        "NoofTxDME": 2,
        "DMEFrequency": 110.05,
        "DMEProcedure": "LFV.FI.P.09-03C",
        "NationalRegulation": "BL 8-2",
        "InternationalStandard": "ICAO Annex 10 Vol 1",
        "Country": "Denmark"
    },
    {
        "Station": "Arvidsjaur",
        "Facility": "E-DME",
        "Ident": "ARV",
        "Periodicity": 365,
        "TypeDME": "Thales 435",
        "NoofTxDME": 2,
        "DMEFrequency": 109.35,
        "DMEProcedure": "LFV.FI.P.09-03A",
        "NationalRegulation": "TSFS 2016-18",
        "InternationalStandard": "ICAO Annex 10 Vol 1",
        "Country": "Sweden"
    },
    {
        "Station": "Backa",
        "Facility": "E-DME",
        "Ident": "BAK",
        "Periodicity": 365,
        "TypeDME": "Thales FSD-45",
        "NoofTxDME": 2,
        "DMEFrequency": 112.7,
        "DMEProcedure": "LFV.FI.P.09-03A",
        "NationalRegulation": "TSFS 2016-18",
        "InternationalStandard": "ICAO Annex 10 Vol 1",
        "Country": "Sweden"
    },
    {
        "Station": "Bunge",
        "Facility": "E-DME",
        "Ident": "BGE",
        "Periodicity": 365,
        "TypeDME": "Thales 435",
        "NoofTxDME": 2,
        "DMEFrequency": 116.6,
        "DMEProcedure": "LFV.FI.P.09-03A",
        "NationalRegulation": "TSFS 2016-18",
        "InternationalStandard": "ICAO Annex 10 Vol 1",
        "Country": "Sweden"
    },
    {
        "Station": "Dals-Långed",
        "Facility": "E-DME",
        "Ident": "FEN",
        "Periodicity": 365,
        "TypeDME": null,
        "NoofTxDME": 2,
        "DMEFrequency": 115.35,
        "DMEProcedure": "LFV.FI.P.09-03A",
        "NationalRegulation": "TSFS 2016-18",
        "InternationalStandard": "ICAO Annex 10 Vol 1",
        "Country": "Sweden"
    },
    {
        "Station": "Färila",
        "Facility": "E-DME",
        "Ident": "FRL",
        "Periodicity": 365,
        "TypeDME": "Thales 435",
        "NoofTxDME": 2,
        "DMEFrequency": 116.5,
        "DMEProcedure": "LFV.FI.P.09-03A",
        "NationalRegulation": "TSFS 2016-18",
        "InternationalStandard": "ICAO Annex 10 Vol 1",
        "Country": "Sweden"
    },
    {
        "Station": "Hoting",
        "Facility": "E-DME",
        "Ident": "HOT",
        "Periodicity": 365,
        "TypeDME": null,
        "NoofTxDME": 2,
        "DMEFrequency": 115.7,
        "DMEProcedure": "LFV.FI.P.09-03A",
        "NationalRegulation": "TSFS 2016-18",
        "InternationalStandard": "ICAO Annex 10 Vol 1",
        "Country": "Sweden"
    },
    {
        "Station": "Mörbylånga",
        "Facility": "E-DME",
        "Ident": "MBL",
        "Periodicity": 365,
        "TypeDME": "Thales 415",
        "NoofTxDME": 2,
        "DMEFrequency": 115.6,
        "DMEProcedure": "LFV.FI.P.09-03A",
        "NationalRegulation": "TSFS 2016-18",
        "InternationalStandard": "ICAO Annex 10 Vol 1",
        "Country": "Sweden"
    },
    {
        "Station": "Pajala",
        "Facility": "E-DME",
        "Ident": "PJL",
        "Periodicity": 365,
        "TypeDME": "Thales 435",
        "NoofTxDME": 2,
        "DMEFrequency": 115.35,
        "DMEProcedure": "LFV.FI.P.09-03A",
        "NationalRegulation": "TSFS 2016-18",
        "InternationalStandard": "ICAO Annex 10 Vol 1",
        "Country": "Sweden"
    },
    {
        "Station": "Ramsele",
        "Facility": "E-DME",
        "Ident": "RAE",
        "Periodicity": 365,
        "TypeDME": null,
        "NoofTxDME": 2,
        "DMEFrequency": 116.7,
        "DMEProcedure": "LFV.FI.P.09-03A",
        "NationalRegulation": "TSFS 2016-18",
        "InternationalStandard": "ICAO Annex 10 Vol 1",
        "Country": "Sweden"
    },
    {
        "Station": "Ronneby",
        "Facility": "E-DME",
        "Ident": "RON",
        "Periodicity": 365,
        "TypeDME": null,
        "NoofTxDME": 2,
        "DMEFrequency": 109.2,
        "DMEProcedure": "LFV.FI.P.09-03A",
        "NationalRegulation": "TSFS 2016-18",
        "InternationalStandard": "ICAO Annex 10 Vol 1",
        "Country": "Sweden"
    },
    {
        "Station": "Soppero",
        "Facility": "E-DME",
        "Ident": "SPO",
        "Periodicity": 365,
        "TypeDME": null,
        "NoofTxDME": 2,
        "DMEFrequency": 115.9,
        "DMEProcedure": "LFV.FI.P.09-03A",
        "NationalRegulation": "TSFS 2016-18",
        "InternationalStandard": "ICAO Annex 10 Vol 1",
        "Country": "Sweden"
    },
    {
        "Station": "Sveda",
        "Facility": "E-DME",
        "Ident": "SVD",
        "Periodicity": 365,
        "TypeDME": null,
        "NoofTxDME": 2,
        "DMEFrequency": 116.2,
        "DMEProcedure": "LFV.FI.P.09-03A",
        "NationalRegulation": "TSFS 2016-18",
        "InternationalStandard": "ICAO Annex 10 Vol 1",
        "Country": "Sweden"
    },
    {
        "Station": "Sveg",
        "Facility": "E-DME",
        "Ident": "SVE",
        "Periodicity": 365,
        "TypeDME": null,
        "NoofTxDME": 2,
        "DMEFrequency": 113.95,
        "DMEProcedure": "LFV.FI.P.09-03A",
        "NationalRegulation": "TSFS 2016-18",
        "InternationalStandard": "ICAO Annex 10 Vol 1",
        "Country": "Sweden"
    }
]